lyceum/__init__.py
lyceum/main.py
lyceum/external/__init__.py
lyceum/external/auth/__init__.py
lyceum/external/auth/login.py
lyceum/external/compute/__init__.py
lyceum/external/compute/execution/__init__.py
lyceum/external/compute/execution/config.py
lyceum/external/compute/execution/docker.py
lyceum/external/compute/execution/docker_compose.py
lyceum/external/compute/execution/notebook.py
lyceum/external/compute/execution/python.py
lyceum/external/compute/execution/workloads.py
lyceum/external/compute/inference/__init__.py
lyceum/external/compute/inference/batch.py
lyceum/external/compute/inference/chat.py
lyceum/external/compute/inference/models.py
lyceum/external/general/__init__.py
lyceum/external/vms/__init__.py
lyceum/external/vms/instances.py
lyceum/external/vms/management.py
lyceum/shared/__init__.py
lyceum/shared/config.py
lyceum/shared/display.py
lyceum/shared/imports.py
lyceum/shared/streaming.py
lyceum_cloud_execution_api_client/__init__.py
lyceum_cloud_execution_api_client/api/__init__.py
lyceum_cloud_execution_api_client/models/__init__.py
lyceum_cli-1.0.28.dist-info/METADATA
lyceum_cli-1.0.28.dist-info/WHEEL
lyceum_cli-1.0.28.dist-info/entry_points.txt
lyceum_cli-1.0.28.dist-info/top_level.txt
lyceum_cli-1.0.28.dist-info/RECORD
